luminex/__init__.py
luminex/config_test.py
luminex/delete_infra.py
luminex/delete_stack.py
luminex/etl.py
luminex/infra_setup.py
luminex/configs/__init__.py
luminex/configs/config.yaml
luminex/configs/config_wrapper.py
luminex/data_standardization/__init__.py
luminex/data_standardization/s3_data_loader.py
luminex/data_standardization/s3_data_loader_spark.py
luminex/data_standardization/s3_json_uploader.py
luminex/infrastructure/config_parameter.json
luminex/infrastructure/create-emr-cft.yml
luminex/infrastructure/luminex-bootstrap.sh
luminex/infrastructure/luminex-configurations.yaml
luminex/validation/__init__.py
luminex/validation/infra_validator.py
luminex/validation/s3_validator.py
luminex/validation/stack_name_validator.py
luminex/validation/validate_multiple_files.py
luminex-0.0.2.dist-info/LICENSE.txt
luminex-0.0.2.dist-info/METADATA
luminex-0.0.2.dist-info/WHEEL
luminex-0.0.2.dist-info/top_level.txt
luminex-0.0.2.dist-info/RECORD
