Metadata-Version: 2.1
Name: luminex
Version: 0.0.2
Summary: On the Fly ETL application
Home-page: 
Author-email: devex@dish.com
License: Dish Wireless
License-File: LICENSE.txt
Requires-Dist: pyspark
Requires-Dist: pandas
Requires-Dist: numpy
Requires-Dist: boto3
Requires-Dist: fastparquet
Requires-Dist: pyarrow
Requires-Dist: python-dotenv
Requires-Dist: requests
Requires-Dist: pyyaml
Requires-Dist: PyGithub
